nrpm/__init__.py
nrpm-0.0.0.dist-info/METADATA
nrpm-0.0.0.dist-info/WHEEL
nrpm-0.0.0.dist-info/top_level.txt
nrpm-0.0.0.dist-info/RECORD
