Metadata-Version: 2.1
Name: nrpm
Version: 0.0.0
Summary: Nginx Reverse Proxy Manager - coming soon
Author-email: Jules <nrpm.contact.faculty897@passmail.net>
